rdkit_to_params/__init__.py
rdkit_to_params/_init_mixin.py
rdkit_to_params/_io_mixin.py
rdkit_to_params/_pyrosetta_mixin.py
rdkit_to_params/constraint.py
rdkit_to_params/entries.py
rdkit_to_params/version.py
rdkit_to_params/cli/__init__.py
rdkit_to_params/rdkitside/__init__.py
rdkit_to_params/rdkitside/_rdkit_convert.py
rdkit_to_params/rdkitside/_rdkit_inits.py
rdkit_to_params/rdkitside/_rdkit_prep.py
rdkit_to_params/rdkitside/_rdkit_rename.py
rdkit_to_params/rdkitside/utilities.py
rdkit_to_params-1.3.2.dist-info/licenses/LICENSE
rdkit_to_params-1.3.2.dist-info/METADATA
rdkit_to_params-1.3.2.dist-info/WHEEL
rdkit_to_params-1.3.2.dist-info/entry_points.txt
rdkit_to_params-1.3.2.dist-info/top_level.txt
rdkit_to_params-1.3.2.dist-info/RECORD
