Metadata-Version: 2.4
Name: rdkit_to_params
Version: 1.3.2
Summary: Create or modify Rosetta params files (topology files) from scratch, RDKit mols or another params file.
Author-email: Matteo Ferla <matteo.ferla@gmail.com>
License: MIT
Project-URL: Homepage, https://github.com/matteoferla/rdkit_to_params
Project-URL: Citation, https://advances.sciencemag.org/content/7/16/eabf8711
Classifier: Development Status :: 5 - Production/Stable
Classifier: Intended Audience :: Science/Research
Classifier: Topic :: Scientific/Engineering :: Bio-Informatics
Classifier: Topic :: Scientific/Engineering :: Chemistry
Classifier: License :: OSI Approved :: MIT License
Classifier: Programming Language :: Python :: 3.7
Classifier: Programming Language :: Python :: 3.8
Classifier: Programming Language :: Python :: 3.9
Classifier: Programming Language :: Python :: 3.10
Classifier: Programming Language :: Python :: 3.11
Requires-Python: >=3.6
License-File: LICENSE
Requires-Dist: rdkit
Provides-Extra: test
Requires-Dist: pytest>=6.0; extra == "test"
Requires-Dist: nox; extra == "test"
Requires-Dist: ruff; extra == "test"
Requires-Dist: mypy; extra == "test"
Requires-Dist: radon; extra == "test"
Dynamic: license-file
